pyport/__init__.py
pyport/__init__.pyi
pyport/api_client.py
pyport/constants.py
pyport/error_handling.py
pyport/exceptions.py
pyport/logging.py
pyport/retry.py
pyport/types.py
pyport/action_runs/__init__.py
pyport/action_runs/action_runs_api_svc.py
pyport/action_runs/types.py
pyport/actions/__init__.py
pyport/actions/actions_api_svc.py
pyport/actions/types.py
pyport/apps/__init__.py
pyport/apps/apps_api_svc.py
pyport/apps/types.py
pyport/audit/__init__.py
pyport/audit/audit_api_svc.py
pyport/audit/types.py
pyport/blueprints/__init__.py
pyport/blueprints/blueprint_api_svc.py
pyport/blueprints/blueprint_api_svc.pyi
pyport/blueprints/types.py
pyport/checklist/__init__.py
pyport/checklist/checklist_api_svc.py
pyport/checklist/types.py
pyport/client/__init__.py
pyport/client/__init__.pyi
pyport/client/auth.py
pyport/client/client.py
pyport/client/client.pyi
pyport/client/request.py
pyport/custom/__init__.py
pyport/custom/custom_api_svc.py
pyport/data_sources/__init__.py
pyport/data_sources/data_sources_api_svc.py
pyport/data_sources/types.py
pyport/entities/__init__.py
pyport/entities/entities_api_svc.py
pyport/entities/entities_api_svc.pyi
pyport/entities/types.py
pyport/integrations/__init__.py
pyport/integrations/integrations_api_svc.py
pyport/integrations/types.py
pyport/migrations/__init__.py
pyport/migrations/migrations_api_svc.py
pyport/migrations/types.py
pyport/models/__init__.py
pyport/models/api_category.py
pyport/models/response.py
pyport/organization/__init__.py
pyport/organization/organization_api_svc.py
pyport/organization/types.py
pyport/pages/__init__.py
pyport/pages/pages_api_svc.py
pyport/pages/types.py
pyport/roles/__init__.py
pyport/roles/roles_api_svc.py
pyport/roles/types.py
pyport/scorecards/__init__.py
pyport/scorecards/scorecards_api_svc.py
pyport/scorecards/types.py
pyport/search/__init__.py
pyport/search/search_api_svc.py
pyport/search/types.py
pyport/services/__init__.py
pyport/services/base_api_service.py
pyport-0.3.3.dist-info/licenses/LICENSE
pyport-0.3.3.dist-info/METADATA
pyport-0.3.3.dist-info/WHEEL
pyport-0.3.3.dist-info/top_level.txt
pyport-0.3.3.dist-info/RECORD
