Metadata-Version: 2.4
Name: pyport
Version: 0.3.3
Summary: Port REST API Wrapper
Author-email: Dan Amzulescu <dan.a@getport.io>
License-Expression: MIT
Classifier: Development Status :: 4 - Beta
Classifier: Intended Audience :: Developers
Classifier: Topic :: Software Development :: Libraries
Classifier: Programming Language :: Python
Classifier: Programming Language :: Python :: 3
Classifier: Programming Language :: Python :: 3.8
Classifier: Programming Language :: Python :: 3.9
Classifier: Programming Language :: Python :: 3.10
Classifier: Programming Language :: Python :: 3.11
Classifier: Programming Language :: Python :: 3.12
Requires-Python: >=3.8
License-File: LICENSE
Requires-Dist: python-dotenv~=1.0.1
Requires-Dist: requests~=2.32.4
Provides-Extra: dev
Requires-Dist: flake8~=7.2.0; extra == "dev"
Requires-Dist: build~=1.2.2; extra == "dev"
Requires-Dist: twine~=6.1.0; extra == "dev"
Dynamic: license-file
